saghetti/__init__.py
saghetti/animation.py
saghetti/cli.py
saghetti-0.2.1.dist-info/entry_points.txt
saghetti-0.2.1.dist-info/LICENSE
saghetti-0.2.1.dist-info/WHEEL
saghetti-0.2.1.dist-info/METADATA
saghetti-0.2.1.dist-info/RECORD
